odoo9_addon_sale_order_general_discount-9.0.1.0.1-py3.8-nspkg.pth
odoo_addons/sale_order_general_discount/README.rst
odoo_addons/sale_order_general_discount/__init__.py
odoo_addons/sale_order_general_discount/__openerp__.py
odoo_addons/sale_order_general_discount/i18n/es.po
odoo_addons/sale_order_general_discount/i18n/sale_order_general_discount.pot
odoo_addons/sale_order_general_discount/models/__init__.py
odoo_addons/sale_order_general_discount/models/res_partner.py
odoo_addons/sale_order_general_discount/models/sale.py
odoo_addons/sale_order_general_discount/readme/CONTRIBUTORS.rst
odoo_addons/sale_order_general_discount/readme/DESCRIPTION.rst
odoo_addons/sale_order_general_discount/readme/INSTALL.rst
odoo_addons/sale_order_general_discount/readme/USAGE.rst
odoo_addons/sale_order_general_discount/static/description/icon.png
odoo_addons/sale_order_general_discount/static/description/index.html
odoo_addons/sale_order_general_discount/tests/__init__.py
odoo_addons/sale_order_general_discount/tests/test_sale_order_general_discount.py
odoo_addons/sale_order_general_discount/views/res_partner_view.xml
odoo_addons/sale_order_general_discount/views/sale_order_view.xml
odoo9_addon_sale_order_general_discount-9.0.1.0.1.dist-info/METADATA
odoo9_addon_sale_order_general_discount-9.0.1.0.1.dist-info/WHEEL
odoo9_addon_sale_order_general_discount-9.0.1.0.1.dist-info/namespace_packages.txt
odoo9_addon_sale_order_general_discount-9.0.1.0.1.dist-info/top_level.txt
odoo9_addon_sale_order_general_discount-9.0.1.0.1.dist-info/RECORD
